odoo/addons/mail_tracking_helpdesk_bounce_ticket/LICENSE
odoo/addons/mail_tracking_helpdesk_bounce_ticket/README.rst
odoo/addons/mail_tracking_helpdesk_bounce_ticket/__init__.py
odoo/addons/mail_tracking_helpdesk_bounce_ticket/__manifest__.py
odoo/addons/mail_tracking_helpdesk_bounce_ticket/images/screen.png
odoo/addons/mail_tracking_helpdesk_bounce_ticket/models/__init__.py
odoo/addons/mail_tracking_helpdesk_bounce_ticket/models/mail_message.py
odoo/addons/mail_tracking_helpdesk_bounce_ticket/static/description/icon.png
odoo/addons/mail_tracking_helpdesk_bounce_ticket/static/description/index.html
odoo/addons/mail_tracking_helpdesk_bounce_ticket/tests/__init__.py
odoo/addons/mail_tracking_helpdesk_bounce_ticket/tests/test_mail_message.py
odoo_addon_mail_tracking_helpdesk_bounce_ticket-16.0.1.0.0.dist-info/METADATA
odoo_addon_mail_tracking_helpdesk_bounce_ticket-16.0.1.0.0.dist-info/WHEEL
odoo_addon_mail_tracking_helpdesk_bounce_ticket-16.0.1.0.0.dist-info/top_level.txt
odoo_addon_mail_tracking_helpdesk_bounce_ticket-16.0.1.0.0.dist-info/RECORD
